{"content":[{"id":"113dd55a","settings":{"eael_parallax_layers_list":[],"structure":"20","ekit_all_conditions_list":[{"_id":"c3ad165","ekit_condition_date":"28-02-2022"}],"ekit_section_parallax_multi_items":[],"hide_widescreen":"hidden-widescreen","hide_desktop":"hidden-desktop","hide_laptop":"hidden-laptop","hide_tablet":"hidden-tablet","tp_display_rules":[{"tp_rule_key":"authentication","tp_rule_operator":"is","tp_rule_authentication_value":"authenticated","_id":"","tp_rule_role_value":"subscriber","tp_rule_date_value":"2022-02-25 to 2022-03-03","tp_rule_time_value":"","tp_rule_day_value":"Monday","tp_rule_os_value":"iphone","tp_rule_browser_value":"ie","tp_rule_page_value":"","tp_rule_post_value":"","tp_rule_static_page_value":"home","tp_rule_post_type_value":"","tp_rule_taxonomy_archive_value":"","tp_rule_term_archive_value":"","tp_rule_term_single_value":"","tp_rule_post_type_archive_value":"","tp_rule_date_archive_value":"","tp_rule_author_archive_value":"","tp_rule_search_results_value":""}]},"elements":[{"id":"1d0d4151","settings":{"_column_size":50,"_inline_size":50,"_inline_size_mobile":50,"padding":{"unit":"px","top":"0","right":"0","bottom":"0","left":"0","isLinked":false},"padding_mobile":{"unit":"px","top":"0","right":"0","bottom":"0","left":"0","isLinked":true},"ekit_all_conditions_list":[{"_id":"02612ba","ekit_condition_date":"28-02-2022"}],"plus_pointer_icon":{"url":"","id":""},"plus_pointer_click_icon":{"url":"","id":""},"pointer_background_image":{"url":"","id":""},"pointer_background_video_fallback":{"url":"","id":""},"pointer_background_slideshow_gallery":[],"plus_column_responsive_list":[]},"elements":[{"id":"7451e6d1","settings":{"gap_columns_custom_mobile":{"unit":"px","size":0,"sizes":[]},"eael_parallax_layers_list":[],"structure":"30","margin_mobile":{"unit":"px","top":"","right":0,"bottom":"","left":0,"isLinked":true},"ekit_all_conditions_list":[{"_id":"900a15a","ekit_condition_date":"28-02-2022"}],"ekit_section_parallax_multi_items":[],"tp_display_rules":[{"tp_rule_key":"authentication","tp_rule_operator":"is","tp_rule_authentication_value":"authenticated","_id":"","tp_rule_role_value":"subscriber","tp_rule_date_value":"2022-02-25 to 2022-03-03","tp_rule_time_value":"","tp_rule_day_value":"Monday","tp_rule_os_value":"iphone","tp_rule_browser_value":"ie","tp_rule_page_value":"","tp_rule_post_value":"","tp_rule_static_page_value":"home","tp_rule_post_type_value":"","tp_rule_taxonomy_archive_value":"","tp_rule_term_archive_value":"","tp_rule_term_single_value":"","tp_rule_post_type_archive_value":"","tp_rule_date_archive_value":"","tp_rule_author_archive_value":"","tp_rule_search_results_value":""}]},"elements":[{"id":"338cc7e6","settings":{"_column_size":33,"_inline_size":null,"space_between_widgets":5,"background_hover_transition":{"unit":"px","size":0.5,"sizes":[]},"box_shadow_box_shadow_type":"yes","box_shadow_box_shadow":{"horizontal":1,"vertical":1,"blur":0,"spread":1,"color":"#D9D9D9"},"box_shadow_hover_box_shadow_type":"yes","box_shadow_hover_box_shadow":{"horizontal":0,"vertical":0,"blur":15,"spread":0,"color":"rgba(0, 0, 0, 0.11)"},"padding":{"unit":"px","top":"15","right":"15","bottom":"15","left":"15","isLinked":true},"ekit_all_conditions_list":[{"_id":"8c540e3","ekit_condition_date":"28-02-2022"}],"padding_mobile":{"unit":"px","top":"15","right":"15","bottom":"15","left":"15","isLinked":true},"plus_pointer_icon":{"url":"","id":""},"plus_pointer_click_icon":{"url":"","id":""},"pointer_background_image":{"url":"","id":""},"pointer_background_video_fallback":{"url":"","id":""},"pointer_background_slideshow_gallery":[],"plus_column_responsive_list":[]},"elements":[{"id":"2187fe2","settings":{"selected_icon":{"value":{"id":"398","url":"http:\/\/localhost\/me.colorvision.design\/wp-content\/uploads\/2022\/03\/AsimovMarketingIcon-bt-omar-bahaa-39-1.svg"},"library":"svg"},"title_text":"Product packaging","description_text":"from EGP 99\u20a4","position":"left","icon_size":{"unit":"px","size":65,"sizes":[]},"title_typography_typography":"custom","title_typography_font_family":"Roboto","title_typography_font_size":{"unit":"px","size":18,"sizes":[]},"title_typography_font_weight":"600","ekit_all_conditions_list":[{"_id":"10ab34c","ekit_condition_date":"28-02-2022"}],"ekit_adv_tooltip_content":"Tooltip Content.","eael_tooltip_section_content":"I am a tooltip","eael_ext_content_protection_password_placeholder":"Enter Password","eael_ext_content_protection_password_submit_btn_txt":"Submit","eael_ext_content_protection_password_incorrect_message":"Password does not match.","__globals__":{"primary_color":"globals\/colors?id=primary","hover_primary_color":"globals\/colors?id=secondary"},"icon_space":{"unit":"px","size":0,"sizes":[]},"icon_space_mobile":{"unit":"px","size":0,"sizes":[]},"title_bottom_space":{"unit":"px","size":5,"sizes":[]},"title_bottom_space_mobile":{"unit":"px","size":5,"sizes":[]},"title_typography_font_size_mobile":{"unit":"px","size":18,"sizes":[]},"tp_display_rules":[{"tp_rule_key":"authentication","tp_rule_operator":"is","tp_rule_authentication_value":"authenticated","_id":"","tp_rule_role_value":"subscriber","tp_rule_date_value":"2022-02-25 to 2022-03-03","tp_rule_time_value":"","tp_rule_day_value":"Monday","tp_rule_os_value":"iphone","tp_rule_browser_value":"ie","tp_rule_page_value":"","tp_rule_post_value":"","tp_rule_static_page_value":"home","tp_rule_post_type_value":"","tp_rule_taxonomy_archive_value":"","tp_rule_term_archive_value":"","tp_rule_term_single_value":"","tp_rule_post_type_archive_value":"","tp_rule_date_archive_value":"","tp_rule_author_archive_value":"","tp_rule_search_results_value":""}]},"elements":[],"isInner":false,"widgetType":"icon-box","elType":"widget"},{"id":"1982e664","settings":{"editor":"Packaging that buyers can't wait to open","ekit_all_conditions_list":[{"_id":"f8d8dc2","ekit_condition_date":"23-01-2022"}],"ekit_adv_tooltip_content":"Tooltip Content.","eael_tooltip_section_content":"I am a tooltip","eael_ext_content_protection_password_placeholder":"Enter Password","eael_ext_content_protection_password_submit_btn_txt":"Submit","eael_ext_content_protection_password_incorrect_message":"Password does not match.","tp_display_rules":[{"tp_rule_key":"authentication","tp_rule_operator":"is","tp_rule_authentication_value":"authenticated","_id":"","tp_rule_role_value":"subscriber","tp_rule_date_value":"2022-02-25 to 2022-03-03","tp_rule_time_value":"","tp_rule_day_value":"Monday","tp_rule_os_value":"iphone","tp_rule_browser_value":"ie","tp_rule_page_value":"","tp_rule_post_value":"","tp_rule_static_page_value":"home","tp_rule_post_type_value":"","tp_rule_taxonomy_archive_value":"","tp_rule_term_archive_value":"","tp_rule_term_single_value":"","tp_rule_post_type_archive_value":"","tp_rule_date_archive_value":"","tp_rule_author_archive_value":"","tp_rule_search_results_value":""}]},"elements":[],"isInner":false,"widgetType":"text-editor","elType":"widget"}],"isInner":true,"elType":"column"},{"id":"e30f444","settings":{"_column_size":33,"_inline_size":null,"space_between_widgets":5,"background_hover_transition":{"unit":"px","size":0.5,"sizes":[]},"box_shadow_box_shadow_type":"yes","box_shadow_box_shadow":{"horizontal":1,"vertical":1,"blur":0,"spread":1,"color":"#D9D9D9"},"box_shadow_hover_box_shadow_type":"yes","box_shadow_hover_box_shadow":{"horizontal":0,"vertical":0,"blur":15,"spread":0,"color":"rgba(0, 0, 0, 0.11)"},"padding":{"unit":"px","top":"15","right":"15","bottom":"15","left":"15","isLinked":true},"ekit_all_conditions_list":[{"_id":"8c540e3","ekit_condition_date":"28-02-2022"}],"padding_mobile":{"unit":"px","top":"15","right":"15","bottom":"15","left":"15","isLinked":true},"plus_pointer_icon":{"url":"","id":""},"plus_pointer_click_icon":{"url":"","id":""},"pointer_background_image":{"url":"","id":""},"pointer_background_video_fallback":{"url":"","id":""},"pointer_background_slideshow_gallery":[],"plus_column_responsive_list":[]},"elements":[{"id":"208ecec6","settings":{"selected_icon":{"value":{"id":"406","url":"http:\/\/localhost\/me.colorvision.design\/wp-content\/uploads\/2022\/03\/AsimovMarketingIcon-bt-omar-bahaa-50-1.svg"},"library":"svg"},"title_text":"Food Packaging","description_text":"from EGP 150\u20a4","position":"left","icon_size":{"unit":"px","size":65,"sizes":[]},"title_typography_typography":"custom","title_typography_font_family":"Roboto","title_typography_font_size":{"unit":"px","size":18,"sizes":[]},"title_typography_font_weight":"600","ekit_all_conditions_list":[{"_id":"10ab34c","ekit_condition_date":"28-02-2022"}],"ekit_adv_tooltip_content":"Tooltip Content.","eael_tooltip_section_content":"I am a tooltip","eael_ext_content_protection_password_placeholder":"Enter Password","eael_ext_content_protection_password_submit_btn_txt":"Submit","eael_ext_content_protection_password_incorrect_message":"Password does not match.","__globals__":{"primary_color":"globals\/colors?id=primary","hover_primary_color":"globals\/colors?id=secondary"},"icon_space":{"unit":"px","size":0,"sizes":[]},"icon_space_mobile":{"unit":"px","size":0,"sizes":[]},"title_bottom_space":{"unit":"px","size":5,"sizes":[]},"title_bottom_space_mobile":{"unit":"px","size":5,"sizes":[]},"title_typography_font_size_mobile":{"unit":"px","size":18,"sizes":[]},"tp_display_rules":[{"tp_rule_key":"authentication","tp_rule_operator":"is","tp_rule_authentication_value":"authenticated","_id":"","tp_rule_role_value":"subscriber","tp_rule_date_value":"2022-02-25 to 2022-03-03","tp_rule_time_value":"","tp_rule_day_value":"Monday","tp_rule_os_value":"iphone","tp_rule_browser_value":"ie","tp_rule_page_value":"","tp_rule_post_value":"","tp_rule_static_page_value":"home","tp_rule_post_type_value":"","tp_rule_taxonomy_archive_value":"","tp_rule_term_archive_value":"","tp_rule_term_single_value":"","tp_rule_post_type_archive_value":"","tp_rule_date_archive_value":"","tp_rule_author_archive_value":"","tp_rule_search_results_value":""}]},"elements":[],"isInner":false,"widgetType":"icon-box","elType":"widget"},{"id":"581f8576","settings":{"editor":"Delicious food packaging that's good enough to eat","ekit_all_conditions_list":[{"_id":"f8d8dc2","ekit_condition_date":"23-01-2022"}],"ekit_adv_tooltip_content":"Tooltip Content.","eael_tooltip_section_content":"I am a tooltip","eael_ext_content_protection_password_placeholder":"Enter Password","eael_ext_content_protection_password_submit_btn_txt":"Submit","eael_ext_content_protection_password_incorrect_message":"Password does not match.","tp_display_rules":[{"tp_rule_key":"authentication","tp_rule_operator":"is","tp_rule_authentication_value":"authenticated","_id":"","tp_rule_role_value":"subscriber","tp_rule_date_value":"2022-02-25 to 2022-03-03","tp_rule_time_value":"","tp_rule_day_value":"Monday","tp_rule_os_value":"iphone","tp_rule_browser_value":"ie","tp_rule_page_value":"","tp_rule_post_value":"","tp_rule_static_page_value":"home","tp_rule_post_type_value":"","tp_rule_taxonomy_archive_value":"","tp_rule_term_archive_value":"","tp_rule_term_single_value":"","tp_rule_post_type_archive_value":"","tp_rule_date_archive_value":"","tp_rule_author_archive_value":"","tp_rule_search_results_value":""}]},"elements":[],"isInner":false,"widgetType":"text-editor","elType":"widget"}],"isInner":true,"elType":"column"},{"id":"3f663f26","settings":{"_column_size":33,"_inline_size":null,"space_between_widgets":5,"background_hover_transition":{"unit":"px","size":0.5,"sizes":[]},"box_shadow_box_shadow_type":"yes","box_shadow_box_shadow":{"horizontal":2,"vertical":2,"blur":0,"spread":0,"color":"#D9D9D9"},"box_shadow_hover_box_shadow_type":"yes","box_shadow_hover_box_shadow":{"horizontal":0,"vertical":0,"blur":15,"spread":0,"color":"rgba(0, 0, 0, 0.11)"},"padding":{"unit":"px","top":"15","right":"15","bottom":"15","left":"15","isLinked":true},"ekit_all_conditions_list":[{"_id":"8c540e3","ekit_condition_date":"28-02-2022"}],"padding_mobile":{"unit":"px","top":"15","right":"15","bottom":"15","left":"15","isLinked":true},"plus_pointer_icon":{"url":"","id":""},"plus_pointer_click_icon":{"url":"","id":""},"pointer_background_image":{"url":"","id":""},"pointer_background_video_fallback":{"url":"","id":""},"pointer_background_slideshow_gallery":[],"plus_column_responsive_list":[]},"elements":[{"id":"4260e6d9","settings":{"selected_icon":{"value":{"id":"407","url":"http:\/\/localhost\/me.colorvision.design\/wp-content\/uploads\/2022\/03\/AsimovMarketingIcon-bt-omar-bahaa-56-1.svg"},"library":"svg"},"title_text":"Retail Packaging","description_text":"from EGP 150\u20a4","position":"left","icon_size":{"unit":"px","size":65,"sizes":[]},"title_typography_typography":"custom","title_typography_font_family":"Roboto","title_typography_font_size":{"unit":"px","size":18,"sizes":[]},"title_typography_font_weight":"600","ekit_all_conditions_list":[{"_id":"10ab34c","ekit_condition_date":"28-02-2022"}],"ekit_adv_tooltip_content":"Tooltip Content.","eael_tooltip_section_content":"I am a tooltip","eael_ext_content_protection_password_placeholder":"Enter Password","eael_ext_content_protection_password_submit_btn_txt":"Submit","eael_ext_content_protection_password_incorrect_message":"Password does not match.","__globals__":{"primary_color":"globals\/colors?id=primary","hover_primary_color":"globals\/colors?id=secondary"},"icon_space":{"unit":"px","size":0,"sizes":[]},"icon_space_mobile":{"unit":"px","size":0,"sizes":[]},"title_bottom_space":{"unit":"px","size":5,"sizes":[]},"title_bottom_space_mobile":{"unit":"px","size":5,"sizes":[]},"title_typography_font_size_mobile":{"unit":"px","size":18,"sizes":[]},"tp_display_rules":[{"tp_rule_key":"authentication","tp_rule_operator":"is","tp_rule_authentication_value":"authenticated","_id":"","tp_rule_role_value":"subscriber","tp_rule_date_value":"2022-02-25 to 2022-03-03","tp_rule_time_value":"","tp_rule_day_value":"Monday","tp_rule_os_value":"iphone","tp_rule_browser_value":"ie","tp_rule_page_value":"","tp_rule_post_value":"","tp_rule_static_page_value":"home","tp_rule_post_type_value":"","tp_rule_taxonomy_archive_value":"","tp_rule_term_archive_value":"","tp_rule_term_single_value":"","tp_rule_post_type_archive_value":"","tp_rule_date_archive_value":"","tp_rule_author_archive_value":"","tp_rule_search_results_value":""}]},"elements":[],"isInner":false,"widgetType":"icon-box","elType":"widget"},{"id":"4f288bcd","settings":{"editor":"Retail packaging that sells your product","ekit_all_conditions_list":[{"_id":"f8d8dc2","ekit_condition_date":"23-01-2022"}],"ekit_adv_tooltip_content":"Tooltip Content.","eael_tooltip_section_content":"I am a tooltip","eael_ext_content_protection_password_placeholder":"Enter Password","eael_ext_content_protection_password_submit_btn_txt":"Submit","eael_ext_content_protection_password_incorrect_message":"Password does not match.","tp_display_rules":[{"tp_rule_key":"authentication","tp_rule_operator":"is","tp_rule_authentication_value":"authenticated","_id":"","tp_rule_role_value":"subscriber","tp_rule_date_value":"2022-02-25 to 2022-03-03","tp_rule_time_value":"","tp_rule_day_value":"Monday","tp_rule_os_value":"iphone","tp_rule_browser_value":"ie","tp_rule_page_value":"","tp_rule_post_value":"","tp_rule_static_page_value":"home","tp_rule_post_type_value":"","tp_rule_taxonomy_archive_value":"","tp_rule_term_archive_value":"","tp_rule_term_single_value":"","tp_rule_post_type_archive_value":"","tp_rule_date_archive_value":"","tp_rule_author_archive_value":"","tp_rule_search_results_value":""}]},"elements":[],"isInner":false,"widgetType":"text-editor","elType":"widget"}],"isInner":true,"elType":"column"}],"isInner":true,"elType":"section"},{"id":"7997c46c","settings":{"gap_columns_custom_mobile":{"unit":"px","size":0,"sizes":[]},"eael_parallax_layers_list":[],"margin_mobile":{"unit":"px","top":"","right":0,"bottom":"","left":0,"isLinked":true},"ekit_all_conditions_list":[{"_id":"900a15a","ekit_condition_date":"28-02-2022"}],"ekit_section_parallax_multi_items":[],"tp_display_rules":[{"tp_rule_key":"authentication","tp_rule_operator":"is","tp_rule_authentication_value":"authenticated","_id":"","tp_rule_role_value":"subscriber","tp_rule_date_value":"2022-02-25 to 2022-03-03","tp_rule_time_value":"","tp_rule_day_value":"Monday","tp_rule_os_value":"iphone","tp_rule_browser_value":"ie","tp_rule_page_value":"","tp_rule_post_value":"","tp_rule_static_page_value":"home","tp_rule_post_type_value":"","tp_rule_taxonomy_archive_value":"","tp_rule_term_archive_value":"","tp_rule_term_single_value":"","tp_rule_post_type_archive_value":"","tp_rule_date_archive_value":"","tp_rule_author_archive_value":"","tp_rule_search_results_value":""}]},"elements":[{"id":"5c1ba66d","settings":{"_column_size":100,"_inline_size":null,"space_between_widgets":5,"background_hover_transition":{"unit":"px","size":0.5,"sizes":[]},"box_shadow_box_shadow_type":"yes","box_shadow_box_shadow":{"horizontal":2,"vertical":0,"blur":0,"spread":0,"color":"#D9D9D9"},"box_shadow_hover_box_shadow_type":"yes","box_shadow_hover_box_shadow":{"horizontal":0,"vertical":0,"blur":15,"spread":0,"color":"rgba(0, 0, 0, 0.11)"},"padding":{"unit":"px","top":"15","right":"15","bottom":"15","left":"15","isLinked":true},"ekit_all_conditions_list":[{"_id":"8c540e3","ekit_condition_date":"28-02-2022"}],"padding_mobile":{"unit":"px","top":"15","right":"15","bottom":"15","left":"15","isLinked":true},"plus_pointer_icon":{"url":"","id":""},"plus_pointer_click_icon":{"url":"","id":""},"pointer_background_image":{"url":"","id":""},"pointer_background_video_fallback":{"url":"","id":""},"pointer_background_slideshow_gallery":[],"plus_column_responsive_list":[]},"elements":[{"id":"6bb3c464","settings":{"selected_icon":{"value":{"id":"408","url":"http:\/\/localhost\/me.colorvision.design\/wp-content\/uploads\/2022\/03\/AsimovMarketingIcon-bt-omar-bahaa-55-1.svg"},"library":"svg"},"title_text":" Beverage Label","description_text":"from EGP 75\u20a4","position":"left","icon_size":{"unit":"px","size":65,"sizes":[]},"title_typography_typography":"custom","title_typography_font_family":"Roboto","title_typography_font_size":{"unit":"px","size":18,"sizes":[]},"title_typography_font_weight":"600","ekit_all_conditions_list":[{"_id":"10ab34c","ekit_condition_date":"28-02-2022"}],"ekit_adv_tooltip_content":"Tooltip Content.","eael_tooltip_section_content":"I am a tooltip","eael_ext_content_protection_password_placeholder":"Enter Password","eael_ext_content_protection_password_submit_btn_txt":"Submit","eael_ext_content_protection_password_incorrect_message":"Password does not match.","__globals__":{"primary_color":"globals\/colors?id=primary","hover_primary_color":"globals\/colors?id=secondary"},"icon_space":{"unit":"px","size":0,"sizes":[]},"icon_space_mobile":{"unit":"px","size":0,"sizes":[]},"title_bottom_space":{"unit":"px","size":5,"sizes":[]},"title_bottom_space_mobile":{"unit":"px","size":5,"sizes":[]},"title_typography_font_size_mobile":{"unit":"px","size":18,"sizes":[]},"tp_display_rules":[{"tp_rule_key":"authentication","tp_rule_operator":"is","tp_rule_authentication_value":"authenticated","_id":"","tp_rule_role_value":"subscriber","tp_rule_date_value":"2022-02-25 to 2022-03-03","tp_rule_time_value":"","tp_rule_day_value":"Monday","tp_rule_os_value":"iphone","tp_rule_browser_value":"ie","tp_rule_page_value":"","tp_rule_post_value":"","tp_rule_static_page_value":"home","tp_rule_post_type_value":"","tp_rule_taxonomy_archive_value":"","tp_rule_term_archive_value":"","tp_rule_term_single_value":"","tp_rule_post_type_archive_value":"","tp_rule_date_archive_value":"","tp_rule_author_archive_value":"","tp_rule_search_results_value":""}]},"elements":[],"isInner":false,"widgetType":"icon-box","elType":"widget"},{"id":"7bed57c0","settings":{"editor":"A refreshing beverage label","ekit_all_conditions_list":[{"_id":"f8d8dc2","ekit_condition_date":"23-01-2022"}],"ekit_adv_tooltip_content":"Tooltip Content.","eael_tooltip_section_content":"I am a tooltip","eael_ext_content_protection_password_placeholder":"Enter Password","eael_ext_content_protection_password_submit_btn_txt":"Submit","eael_ext_content_protection_password_incorrect_message":"Password does not match.","tp_display_rules":[{"tp_rule_key":"authentication","tp_rule_operator":"is","tp_rule_authentication_value":"authenticated","_id":"","tp_rule_role_value":"subscriber","tp_rule_date_value":"2022-02-25 to 2022-03-03","tp_rule_time_value":"","tp_rule_day_value":"Monday","tp_rule_os_value":"iphone","tp_rule_browser_value":"ie","tp_rule_page_value":"","tp_rule_post_value":"","tp_rule_static_page_value":"home","tp_rule_post_type_value":"","tp_rule_taxonomy_archive_value":"","tp_rule_term_archive_value":"","tp_rule_term_single_value":"","tp_rule_post_type_archive_value":"","tp_rule_date_archive_value":"","tp_rule_author_archive_value":"","tp_rule_search_results_value":""}]},"elements":[],"isInner":false,"widgetType":"text-editor","elType":"widget"}],"isInner":true,"elType":"column"}],"isInner":true,"elType":"section"}],"isInner":false,"elType":"column"},{"id":"5c892c21","settings":{"_column_size":50,"_inline_size":50,"_inline_size_mobile":50,"padding":{"unit":"px","top":"0","right":"0","bottom":"0","left":"0","isLinked":false},"padding_mobile":{"unit":"px","top":"0","right":"0","bottom":"0","left":"0","isLinked":true},"ekit_all_conditions_list":[{"_id":"18e9ea8","ekit_condition_date":"28-02-2022"}],"plus_pointer_icon":{"url":"","id":""},"plus_pointer_click_icon":{"url":"","id":""},"pointer_background_image":{"url":"","id":""},"pointer_background_video_fallback":{"url":"","id":""},"pointer_background_slideshow_gallery":[],"plus_column_responsive_list":[]},"elements":[{"id":"493ea49e","settings":{"eael_parallax_layers_list":[],"structure":"30","ekit_all_conditions_list":[{"_id":"900a15a","ekit_condition_date":"28-02-2022"}],"ekit_section_parallax_multi_items":[],"tp_display_rules":[{"tp_rule_key":"authentication","tp_rule_operator":"is","tp_rule_authentication_value":"authenticated","_id":"","tp_rule_role_value":"subscriber","tp_rule_date_value":"2022-02-25 to 2022-03-03","tp_rule_time_value":"","tp_rule_day_value":"Monday","tp_rule_os_value":"iphone","tp_rule_browser_value":"ie","tp_rule_page_value":"","tp_rule_post_value":"","tp_rule_static_page_value":"home","tp_rule_post_type_value":"","tp_rule_taxonomy_archive_value":"","tp_rule_term_archive_value":"","tp_rule_term_single_value":"","tp_rule_post_type_archive_value":"","tp_rule_date_archive_value":"","tp_rule_author_archive_value":"","tp_rule_search_results_value":""}]},"elements":[{"id":"27027193","settings":{"_column_size":33,"_inline_size":null,"space_between_widgets":5,"background_hover_transition":{"unit":"px","size":0.5,"sizes":[]},"box_shadow_box_shadow_type":"yes","box_shadow_box_shadow":{"horizontal":0,"vertical":2,"blur":0,"spread":0,"color":"#D9D9D9"},"box_shadow_hover_box_shadow_type":"yes","box_shadow_hover_box_shadow":{"horizontal":0,"vertical":0,"blur":15,"spread":0,"color":"rgba(0, 0, 0, 0.11)"},"padding":{"unit":"px","top":"15","right":"15","bottom":"15","left":"15","isLinked":true},"ekit_all_conditions_list":[{"_id":"8c540e3","ekit_condition_date":"28-02-2022"}],"padding_mobile":{"unit":"px","top":"15","right":"15","bottom":"15","left":"15","isLinked":true},"plus_pointer_icon":{"url":"","id":""},"plus_pointer_click_icon":{"url":"","id":""},"pointer_background_image":{"url":"","id":""},"pointer_background_video_fallback":{"url":"","id":""},"pointer_background_slideshow_gallery":[],"plus_column_responsive_list":[]},"elements":[{"id":"5bb0ff42","settings":{"selected_icon":{"value":{"id":"409","url":"http:\/\/localhost\/me.colorvision.design\/wp-content\/uploads\/2022\/03\/AsimovMarketingIcon-bt-omar-bahaa-81-1.svg"},"library":"svg"},"title_text":"Cosmetics Packaging","description_text":"from EGP 75\u20a4","position":"left","icon_size":{"unit":"px","size":65,"sizes":[]},"title_typography_typography":"custom","title_typography_font_family":"Roboto","title_typography_font_size":{"unit":"px","size":18,"sizes":[]},"title_typography_font_weight":"600","ekit_all_conditions_list":[{"_id":"10ab34c","ekit_condition_date":"28-02-2022"}],"ekit_adv_tooltip_content":"Tooltip Content.","eael_tooltip_section_content":"I am a tooltip","eael_ext_content_protection_password_placeholder":"Enter Password","eael_ext_content_protection_password_submit_btn_txt":"Submit","eael_ext_content_protection_password_incorrect_message":"Password does not match.","__globals__":{"primary_color":"globals\/colors?id=primary","hover_primary_color":"globals\/colors?id=secondary"},"icon_space":{"unit":"px","size":0,"sizes":[]},"icon_space_mobile":{"unit":"px","size":0,"sizes":[]},"title_bottom_space":{"unit":"px","size":5,"sizes":[]},"title_bottom_space_mobile":{"unit":"px","size":5,"sizes":[]},"title_typography_font_size_mobile":{"unit":"px","size":18,"sizes":[]},"tp_display_rules":[{"tp_rule_key":"authentication","tp_rule_operator":"is","tp_rule_authentication_value":"authenticated","_id":"","tp_rule_role_value":"subscriber","tp_rule_date_value":"2022-02-25 to 2022-03-03","tp_rule_time_value":"","tp_rule_day_value":"Monday","tp_rule_os_value":"iphone","tp_rule_browser_value":"ie","tp_rule_page_value":"","tp_rule_post_value":"","tp_rule_static_page_value":"home","tp_rule_post_type_value":"","tp_rule_taxonomy_archive_value":"","tp_rule_term_archive_value":"","tp_rule_term_single_value":"","tp_rule_post_type_archive_value":"","tp_rule_date_archive_value":"","tp_rule_author_archive_value":"","tp_rule_search_results_value":""}]},"elements":[],"isInner":false,"widgetType":"icon-box","elType":"widget"},{"id":"75168d42","settings":{"editor":"Cosmetics packaging that makes you look good","ekit_all_conditions_list":[{"_id":"f8d8dc2","ekit_condition_date":"23-01-2022"}],"ekit_adv_tooltip_content":"Tooltip Content.","eael_tooltip_section_content":"I am a tooltip","eael_ext_content_protection_password_placeholder":"Enter Password","eael_ext_content_protection_password_submit_btn_txt":"Submit","eael_ext_content_protection_password_incorrect_message":"Password does not match.","tp_display_rules":[{"tp_rule_key":"authentication","tp_rule_operator":"is","tp_rule_authentication_value":"authenticated","_id":"","tp_rule_role_value":"subscriber","tp_rule_date_value":"2022-02-25 to 2022-03-03","tp_rule_time_value":"","tp_rule_day_value":"Monday","tp_rule_os_value":"iphone","tp_rule_browser_value":"ie","tp_rule_page_value":"","tp_rule_post_value":"","tp_rule_static_page_value":"home","tp_rule_post_type_value":"","tp_rule_taxonomy_archive_value":"","tp_rule_term_archive_value":"","tp_rule_term_single_value":"","tp_rule_post_type_archive_value":"","tp_rule_date_archive_value":"","tp_rule_author_archive_value":"","tp_rule_search_results_value":""}]},"elements":[],"isInner":false,"widgetType":"text-editor","elType":"widget"}],"isInner":true,"elType":"column"},{"id":"36190936","settings":{"_column_size":33,"_inline_size":null,"space_between_widgets":5,"background_hover_transition":{"unit":"px","size":0.5,"sizes":[]},"box_shadow_box_shadow_type":"yes","box_shadow_box_shadow":{"horizontal":0,"vertical":2,"blur":0,"spread":0,"color":"#D9D9D9"},"box_shadow_hover_box_shadow_type":"yes","box_shadow_hover_box_shadow":{"horizontal":0,"vertical":0,"blur":15,"spread":0,"color":"rgba(0, 0, 0, 0.11)"},"padding":{"unit":"px","top":"15","right":"15","bottom":"15","left":"15","isLinked":true},"ekit_all_conditions_list":[{"_id":"8c540e3","ekit_condition_date":"28-02-2022"}],"padding_mobile":{"unit":"px","top":"15","right":"15","bottom":"15","left":"15","isLinked":true},"plus_pointer_icon":{"url":"","id":""},"plus_pointer_click_icon":{"url":"","id":""},"pointer_background_image":{"url":"","id":""},"pointer_background_video_fallback":{"url":"","id":""},"pointer_background_slideshow_gallery":[],"plus_column_responsive_list":[]},"elements":[{"id":"4320939b","settings":{"selected_icon":{"value":{"id":"410","url":"http:\/\/localhost\/me.colorvision.design\/wp-content\/uploads\/2022\/03\/AsimovMarketingIcon-bt-omar-bahaa-46-1.svg"},"library":"svg"},"title_text":"Product label","description_text":"from EGP 75\u20a4","position":"left","icon_size":{"unit":"px","size":65,"sizes":[]},"title_typography_typography":"custom","title_typography_font_family":"Roboto","title_typography_font_size":{"unit":"px","size":18,"sizes":[]},"title_typography_font_weight":"600","ekit_all_conditions_list":[{"_id":"10ab34c","ekit_condition_date":"28-02-2022"}],"ekit_adv_tooltip_content":"Tooltip Content.","eael_tooltip_section_content":"I am a tooltip","eael_ext_content_protection_password_placeholder":"Enter Password","eael_ext_content_protection_password_submit_btn_txt":"Submit","eael_ext_content_protection_password_incorrect_message":"Password does not match.","__globals__":{"primary_color":"globals\/colors?id=primary","hover_primary_color":"globals\/colors?id=secondary"},"icon_space":{"unit":"px","size":0,"sizes":[]},"icon_space_mobile":{"unit":"px","size":0,"sizes":[]},"title_bottom_space":{"unit":"px","size":5,"sizes":[]},"title_bottom_space_mobile":{"unit":"px","size":5,"sizes":[]},"title_typography_font_size_mobile":{"unit":"px","size":18,"sizes":[]},"tp_display_rules":[{"tp_rule_key":"authentication","tp_rule_operator":"is","tp_rule_authentication_value":"authenticated","_id":"","tp_rule_role_value":"subscriber","tp_rule_date_value":"2022-02-25 to 2022-03-03","tp_rule_time_value":"","tp_rule_day_value":"Monday","tp_rule_os_value":"iphone","tp_rule_browser_value":"ie","tp_rule_page_value":"","tp_rule_post_value":"","tp_rule_static_page_value":"home","tp_rule_post_type_value":"","tp_rule_taxonomy_archive_value":"","tp_rule_term_archive_value":"","tp_rule_term_single_value":"","tp_rule_post_type_archive_value":"","tp_rule_date_archive_value":"","tp_rule_author_archive_value":"","tp_rule_search_results_value":""}]},"elements":[],"isInner":false,"widgetType":"icon-box","elType":"widget"},{"id":"30ea1dd2","settings":{"editor":"Product labels that stand out on shelves","ekit_all_conditions_list":[{"_id":"f8d8dc2","ekit_condition_date":"23-01-2022"}],"ekit_adv_tooltip_content":"Tooltip Content.","eael_tooltip_section_content":"I am a tooltip","eael_ext_content_protection_password_placeholder":"Enter Password","eael_ext_content_protection_password_submit_btn_txt":"Submit","eael_ext_content_protection_password_incorrect_message":"Password does not match.","tp_display_rules":[{"tp_rule_key":"authentication","tp_rule_operator":"is","tp_rule_authentication_value":"authenticated","_id":"","tp_rule_role_value":"subscriber","tp_rule_date_value":"2022-02-25 to 2022-03-03","tp_rule_time_value":"","tp_rule_day_value":"Monday","tp_rule_os_value":"iphone","tp_rule_browser_value":"ie","tp_rule_page_value":"","tp_rule_post_value":"","tp_rule_static_page_value":"home","tp_rule_post_type_value":"","tp_rule_taxonomy_archive_value":"","tp_rule_term_archive_value":"","tp_rule_term_single_value":"","tp_rule_post_type_archive_value":"","tp_rule_date_archive_value":"","tp_rule_author_archive_value":"","tp_rule_search_results_value":""}]},"elements":[],"isInner":false,"widgetType":"text-editor","elType":"widget"}],"isInner":true,"elType":"column"},{"id":"5384e2cf","settings":{"_column_size":33,"_inline_size":null,"space_between_widgets":5,"background_hover_transition":{"unit":"px","size":0.5,"sizes":[]},"box_shadow_box_shadow_type":"yes","box_shadow_box_shadow":{"horizontal":0,"vertical":2,"blur":0,"spread":0,"color":"#D9D9D9"},"box_shadow_hover_box_shadow_type":"yes","box_shadow_hover_box_shadow":{"horizontal":0,"vertical":0,"blur":15,"spread":0,"color":"rgba(0, 0, 0, 0.11)"},"padding":{"unit":"px","top":"15","right":"15","bottom":"15","left":"15","isLinked":true},"ekit_all_conditions_list":[{"_id":"8c540e3","ekit_condition_date":"28-02-2022"}],"padding_mobile":{"unit":"px","top":"15","right":"15","bottom":"15","left":"15","isLinked":true},"plus_pointer_icon":{"url":"","id":""},"plus_pointer_click_icon":{"url":"","id":""},"pointer_background_image":{"url":"","id":""},"pointer_background_video_fallback":{"url":"","id":""},"pointer_background_slideshow_gallery":[],"plus_column_responsive_list":[]},"elements":[{"id":"339c3906","settings":{"selected_icon":{"value":{"id":"411","url":"http:\/\/localhost\/me.colorvision.design\/wp-content\/uploads\/2022\/03\/AsimovMarketingIcon-bt-omar-bahaa-57-1.svg"},"library":"svg"},"title_text":"Food Label","description_text":"from EGP 75\u20a4","position":"left","icon_size":{"unit":"px","size":65,"sizes":[]},"title_typography_typography":"custom","title_typography_font_family":"Roboto","title_typography_font_size":{"unit":"px","size":18,"sizes":[]},"title_typography_font_weight":"600","ekit_all_conditions_list":[{"_id":"10ab34c","ekit_condition_date":"28-02-2022"}],"ekit_adv_tooltip_content":"Tooltip Content.","eael_tooltip_section_content":"I am a tooltip","eael_ext_content_protection_password_placeholder":"Enter Password","eael_ext_content_protection_password_submit_btn_txt":"Submit","eael_ext_content_protection_password_incorrect_message":"Password does not match.","__globals__":{"primary_color":"globals\/colors?id=primary","hover_primary_color":"globals\/colors?id=secondary"},"icon_space":{"unit":"px","size":0,"sizes":[]},"icon_space_mobile":{"unit":"px","size":0,"sizes":[]},"title_bottom_space":{"unit":"px","size":5,"sizes":[]},"title_bottom_space_mobile":{"unit":"px","size":5,"sizes":[]},"title_typography_font_size_mobile":{"unit":"px","size":18,"sizes":[]},"tp_display_rules":[{"tp_rule_key":"authentication","tp_rule_operator":"is","tp_rule_authentication_value":"authenticated","_id":"","tp_rule_role_value":"subscriber","tp_rule_date_value":"2022-02-25 to 2022-03-03","tp_rule_time_value":"","tp_rule_day_value":"Monday","tp_rule_os_value":"iphone","tp_rule_browser_value":"ie","tp_rule_page_value":"","tp_rule_post_value":"","tp_rule_static_page_value":"home","tp_rule_post_type_value":"","tp_rule_taxonomy_archive_value":"","tp_rule_term_archive_value":"","tp_rule_term_single_value":"","tp_rule_post_type_archive_value":"","tp_rule_date_archive_value":"","tp_rule_author_archive_value":"","tp_rule_search_results_value":""}]},"elements":[],"isInner":false,"widgetType":"icon-box","elType":"widget"},{"id":"4196bf0f","settings":{"editor":"Food labels as tasty as the product inside","ekit_all_conditions_list":[{"_id":"f8d8dc2","ekit_condition_date":"23-01-2022"}],"ekit_adv_tooltip_content":"Tooltip Content.","eael_tooltip_section_content":"I am a tooltip","eael_ext_content_protection_password_placeholder":"Enter Password","eael_ext_content_protection_password_submit_btn_txt":"Submit","eael_ext_content_protection_password_incorrect_message":"Password does not match.","tp_display_rules":[{"tp_rule_key":"authentication","tp_rule_operator":"is","tp_rule_authentication_value":"authenticated","_id":"","tp_rule_role_value":"subscriber","tp_rule_date_value":"2022-02-25 to 2022-03-03","tp_rule_time_value":"","tp_rule_day_value":"Monday","tp_rule_os_value":"iphone","tp_rule_browser_value":"ie","tp_rule_page_value":"","tp_rule_post_value":"","tp_rule_static_page_value":"home","tp_rule_post_type_value":"","tp_rule_taxonomy_archive_value":"","tp_rule_term_archive_value":"","tp_rule_term_single_value":"","tp_rule_post_type_archive_value":"","tp_rule_date_archive_value":"","tp_rule_author_archive_value":"","tp_rule_search_results_value":""}]},"elements":[],"isInner":false,"widgetType":"text-editor","elType":"widget"}],"isInner":true,"elType":"column"}],"isInner":true,"elType":"section"},{"id":"45fb0822","settings":{"eael_parallax_layers_list":[],"ekit_all_conditions_list":[{"_id":"900a15a","ekit_condition_date":"28-02-2022"}],"ekit_section_parallax_multi_items":[],"tp_display_rules":[{"tp_rule_key":"authentication","tp_rule_operator":"is","tp_rule_authentication_value":"authenticated","_id":"","tp_rule_role_value":"subscriber","tp_rule_date_value":"2022-02-25 to 2022-03-03","tp_rule_time_value":"","tp_rule_day_value":"Monday","tp_rule_os_value":"iphone","tp_rule_browser_value":"ie","tp_rule_page_value":"","tp_rule_post_value":"","tp_rule_static_page_value":"home","tp_rule_post_type_value":"","tp_rule_taxonomy_archive_value":"","tp_rule_term_archive_value":"","tp_rule_term_single_value":"","tp_rule_post_type_archive_value":"","tp_rule_date_archive_value":"","tp_rule_author_archive_value":"","tp_rule_search_results_value":""}]},"elements":[{"id":"2433f3b4","settings":{"_column_size":100,"_inline_size":null,"space_between_widgets":5,"background_hover_transition":{"unit":"px","size":0.5,"sizes":[]},"box_shadow_box_shadow_type":"yes","box_shadow_box_shadow":{"horizontal":0,"vertical":0,"blur":0,"spread":0,"color":"#D9D9D9"},"box_shadow_hover_box_shadow_type":"yes","box_shadow_hover_box_shadow":{"horizontal":0,"vertical":0,"blur":15,"spread":0,"color":"rgba(0, 0, 0, 0.11)"},"padding":{"unit":"px","top":"15","right":"15","bottom":"15","left":"15","isLinked":true},"ekit_all_conditions_list":[{"_id":"8c540e3","ekit_condition_date":"28-02-2022"}],"padding_mobile":{"unit":"px","top":"15","right":"15","bottom":"15","left":"15","isLinked":true},"plus_pointer_icon":{"url":"","id":""},"plus_pointer_click_icon":{"url":"","id":""},"pointer_background_image":{"url":"","id":""},"pointer_background_video_fallback":{"url":"","id":""},"pointer_background_slideshow_gallery":[],"plus_column_responsive_list":[]},"elements":[{"id":"68137a31","settings":{"selected_icon":{"value":{"id":"412","url":"http:\/\/localhost\/me.colorvision.design\/wp-content\/uploads\/2022\/03\/AsimovMarketingIcon-bt-omar-bahaa-74-1.svg"},"library":"svg"},"title_text":"Other packaging or label","description_text":"from EGP 99\u20a4","position":"left","icon_size":{"unit":"px","size":65,"sizes":[]},"title_typography_typography":"custom","title_typography_font_family":"Roboto","title_typography_font_size":{"unit":"px","size":18,"sizes":[]},"title_typography_font_weight":"600","ekit_all_conditions_list":[{"_id":"10ab34c","ekit_condition_date":"28-02-2022"}],"ekit_adv_tooltip_content":"Tooltip Content.","eael_tooltip_section_content":"I am a tooltip","eael_ext_content_protection_password_placeholder":"Enter Password","eael_ext_content_protection_password_submit_btn_txt":"Submit","eael_ext_content_protection_password_incorrect_message":"Password does not match.","__globals__":{"primary_color":"globals\/colors?id=primary","hover_primary_color":"globals\/colors?id=secondary"},"icon_space":{"unit":"px","size":0,"sizes":[]},"icon_space_mobile":{"unit":"px","size":0,"sizes":[]},"title_bottom_space":{"unit":"px","size":5,"sizes":[]},"title_bottom_space_mobile":{"unit":"px","size":5,"sizes":[]},"title_typography_font_size_mobile":{"unit":"px","size":18,"sizes":[]},"tp_display_rules":[{"tp_rule_key":"authentication","tp_rule_operator":"is","tp_rule_authentication_value":"authenticated","_id":"","tp_rule_role_value":"subscriber","tp_rule_date_value":"2022-02-25 to 2022-03-03","tp_rule_time_value":"","tp_rule_day_value":"Monday","tp_rule_os_value":"iphone","tp_rule_browser_value":"ie","tp_rule_page_value":"","tp_rule_post_value":"","tp_rule_static_page_value":"home","tp_rule_post_type_value":"","tp_rule_taxonomy_archive_value":"","tp_rule_term_archive_value":"","tp_rule_term_single_value":"","tp_rule_post_type_archive_value":"","tp_rule_date_archive_value":"","tp_rule_author_archive_value":"","tp_rule_search_results_value":""}]},"elements":[],"isInner":false,"widgetType":"icon-box","elType":"widget"},{"id":"37323d5e","settings":{"editor":"Packaging and labels that are outside of the box","ekit_all_conditions_list":[{"_id":"f8d8dc2","ekit_condition_date":"23-01-2022"}],"ekit_adv_tooltip_content":"Tooltip Content.","eael_tooltip_section_content":"I am a tooltip","eael_ext_content_protection_password_placeholder":"Enter Password","eael_ext_content_protection_password_submit_btn_txt":"Submit","eael_ext_content_protection_password_incorrect_message":"Password does not match.","tp_display_rules":[{"tp_rule_key":"authentication","tp_rule_operator":"is","tp_rule_authentication_value":"authenticated","_id":"","tp_rule_role_value":"subscriber","tp_rule_date_value":"2022-02-25 to 2022-03-03","tp_rule_time_value":"","tp_rule_day_value":"Monday","tp_rule_os_value":"iphone","tp_rule_browser_value":"ie","tp_rule_page_value":"","tp_rule_post_value":"","tp_rule_static_page_value":"home","tp_rule_post_type_value":"","tp_rule_taxonomy_archive_value":"","tp_rule_term_archive_value":"","tp_rule_term_single_value":"","tp_rule_post_type_archive_value":"","tp_rule_date_archive_value":"","tp_rule_author_archive_value":"","tp_rule_search_results_value":""}]},"elements":[],"isInner":false,"widgetType":"text-editor","elType":"widget"}],"isInner":true,"elType":"column"}],"isInner":true,"elType":"section"}],"isInner":false,"elType":"column"}],"isInner":false,"elType":"section"}],"settings":{"eael_ext_toc_title":"Table of Contents"},"metadata":{"ekit_post_views_count":"10","tp_render_mode_type":"default","theplus_transient_widgets":"s:6:\"a:0:{}\";"}}